{"features":[{"g":"4K,RL,BK,BL,8M,NJ,]M,hI,BN,AI,XN,]H,gN,9H,oN,gG/oN,gG,5O,^G,?O,VG,OO,PG,4P,DG,[P,7G,;Q,mF,3R,pF,YR,PF,@S,EF,FS,CF,[S,=F","n":"Bever\u012bnas iela"},{"n":"Roosi","g":"SP1,`W,UQ1,`V,;R1,;V,OS1,eT,nS1,?T,cT1,4S,5U1,[R,PU1,9R,CV1,2Q,LV1,kP,bW1,oN,?Y1,oL"},{"n":"Piiri","g":"K^,<A,J^,AA,pp,nB,a[,eC,3[,TD,2[,dD,?[,lD,Pp,SE,l^,LF,j`,7G,3a,=G,3b,nG,kc,aH"},{"g":"6;,GK,p<,pJ,4=,6J,3=,aI,o<,CI,B=,8I,T=,5I,c=,1I,H>,4I,1?,8I,W?,5I,<@,7I,`B,iI,:C,iI,RC,<J,FC,FJ","n":"Gar\u0101\u017eu iela"},{"g":"6j,1^,mg,L_/5f,M^,mg,L_,ai,J`","n":"Tolli"},{"g":"i7,JB,m9,iB,C;,<C,J;,=C,7<,HC,f<,TC,S>,nC/U@,LD,KA,YD/KA,YD,=C,5E,lE,_E,WF,jE,>G,2F,hJ,iF,ON,`G,oN,gG/4Y,oI,?Z,KJ,EZ,MJ,pZ,TJ,8p,1K,Lp,7K,ip,AK,A^,]K/PY,FJ,ZX,;J,fW,oI,XV,pI,5V,SI,YT,=I,ES,iH,4S,eH/A^,]K,E^,^K,S_,lK,b`,7L/S>,nC,U@,LD/d1,m@,R3,GA,_4,YA,i7,JB/oN,gG,HR,[H,4S,eH","n":"Rai\u0146a iela"},{"g":"c>2,TP,e>2,CP,O?2,JO,c?2,2O,1@2,XN,;@2,DN,<@2,?N","n":"Kullerkupu"},{"n":"Uus","g":"Nd,oG,kc,aH,Zc,>I,:c,XI,4c,^I/Ym,5J,ll,DI,Nl,<I,ek,2I,?k,jH,Dj,]H,?i,NH,7i,LH,5h,<H,lf,eG,Vf,cG,me,]G,Oe,ZG,Fe,ZG,od,_G,[d,hG,Nd,oG"},{"n":"T\u00e4he","g":";51,ZN,k41,QO,X41,lO,E41,BP,E41,IP,J41,OP,b51,fP,Q81,UQ,1<1,ER,b<1,SR"},{"n":"Miera iela","g":"IV,C@,XV,B@,cV,E@,RW,Z@,>Y,KA,FY,TA,WY,eA,SZ,eB"},{"n":"Luha","g":"c61,BF,W71,TE/Y;1,`F,`;1,8F,p;1,hE,T;1,^E,B;1,OE,b:1,DE,4:1,?E"},{"n":"T\u00f5rva","g":"L61,AX,n51,YX,P51,7Y,<51,QY,R41,3Z,]31,pZ,d21,M[,E21,f[,]11,Ep,R11,Rp"},{"n":"Blauma\u0146a iela","g":"S>,nC,g=,`D,V=,3E,E=,EE,0=,pE,@<,OF,n:,eG,D:,PH,0:,eH,p9,6I,l8,WI,b8,^I,n7,BJ/n7,BJ,65,:M,93,oN,],@Q,P,QQ"},{"g":"DM2,hW,hK2,XW,MK2,TW,oI2,EW,ZI2,AW,4I2,;W,TH2,7W,0H2,5W,QG2,5W","n":"Sambla"},{"n":"Metsa","g":"iS1,@[,9S1,m[,GQ1,p],<Q1,_],?O1,@],jN1,4],2O1,ep,pO1,:p,nP1,lZ,HQ1,RZ/ES1,4[,HQ1,RZ,aP1,EZ,kK1,hX,8J1,DX,VF1,AW,oC1,5V,8B1,9U,DA1,fT,I>1,_S,M<1,0S,G<1,nR/1W1,6],9W1,np,BW1,Up,7W1,Ep,iS1,@[,ES1,4["},{"g":"cb,YI,4c,^I/^b,XI,cb,YI/3d,:J,Hd,DJ,gd,TJ,<e,_J,Ne,hJ,Ve,lJ/4c,^I,Dc,eI,Jc,hI,3d,:J","n":"Sepa"},{"n":"Sulevi","g":";R1,3B,PS1,mA,;T1,hA,^T1,cA,CU1,YA,UW1,KA,5Z1,:A,2p1,j@/GT1,eB,@T1,<B,;T1,hA"},{"n":"Uus-Koidu","g":"Tf1,6B,9g1,fA,Rg1,[A,;h1,DA,Kh1,:A,kh1,n@,Vi1,g@,Aj1,g@,8k1,k@,`l1,3A,4m1,7A,>m1,8A,Um1,AA,7n1,PA/Tf1,6B,Mf1,;B,ce1,PB,4e1,jB,Qd1,<C,mc1,PC,^c1,XC,Gb1,ED"},{"g":">E,p6,aF,G9,fF,R9,kF,o9,gF,G:,BF,b;,3F,8<,KE,m<,ZD,0>,OC,j>,N@,@A,7@,MA","n":"Cimzes iela"},{"n":"Spordi","g":"WV1,LW,;R1,;V"},{"n":"Pirni","g":"HP2,fQ,gP2,7R,lP2,:R,mP2,AR,lP2,JR,gP2,RR,^P2,[R,EP2,mR,?P2,2S,MO2,YS,^N2,=T,mM2,bT,WM2,3U,PM2,6U,0M2,8U,jK2,BU,_K2,BU,TK2,@U,DK2,;U,MJ2,eT"},{"n":"P\u00e4rnu","g":"W_,OB,i_,PB,Sa,2C,Ob,FC,Rb,RC/Rb,RC,Zb,TC,5g,nD,<g,4E,6g,AE,`f,aE,_f,mE"},{"n":"T\u0113rauda iela","g":"`,pK,93,QL,65,:M"},{"g":"`F2,Xp,>H2,Sp,=I2,Op,GI2,Mp","n":"Ploomipuu"},{"g":"O>,G@,6>,H@,l=,W@,_=,l@,T=,@A,H=,RA,<=,cA,0=,4B,p<,RB,7<,HC","n":"J. Jauna iela"},{"g":"3Y2,_,>Y2,h,BY2,l,BY2,01,dX2,=1,FX2,G1,=X2,C1,4X2,>1,iW2,81","n":"Palu"},{"g":"nc,OL,gc,NL,dc,NL,Aa,:L/n43,=],]43,M],943,m],R33,=^,5o2,]p","n":"S\u00f5pruse"},{"n":"P\u0113tera Radzi\u0146a iela","g":"I2,MF,m2,bF,`3,4G,66,LG,Q7,WG"},{"n":"P\u00e4\u00e4sukese","g":"YO1,Z;1,aN1,L<1,nN1,l<1,mN1,7=1,TN1,G=1"},{"n":"Zvaig\u017e\u0146u iela","g":"JW,eH,YW,eH,=X,dH,hX,iH,JY,oH,9Z,;I,VZ,CI,D[,PI,N[,RI,2p,]I,gp,kI,=_,PJ"},{"g":"K82,@Z,m92,hY,7;2,FY,><2,fX,Z=2,GX,b>2,4X,_?2,VW,a@2,aV,NA2,<V,:B2,=U,@B2,4T,;B2,iS,dA2,0S,>A2,eQ,1A2,JQ","n":"Tibina tee"},{"g":"V<1,O`,b:1,R_,I:1,B_,f91,f^,V71,Q],671,V],461,o]","n":"Kanepi"},{"n":"Savien\u012bbas iela","g":"Rc,=`,Tc,8`,Jd,`],Xd,8]"},{"n":"Muru","g":"?i,NH,Ki,=H,Li,cG,Ui,RG,0j,lF,Uj,LF"},{"g":"j41,EL,<31,hK,<21,XK,O01,3K,no,hJ,dm,8J,Ym,5J","n":"Aia"},{"n":"O\u0161kalna iela","g":"8M,NJ,EK,nI,eI,SI,:H,_I,NG,iI,kE,UJ,0E,=K/hI,CG,>J,UG,kJ,<H,oJ,IH,mJ,SH,eI,SI"},{"g":"dj,LM,dj,OM/Bj,lN,9j,MO/ne,FM,ne,IM,4f,4N,6f,DN,9f,PN,;f,XN,<f,bN,8f,hN,le,nN,Xe,7O,Le,>O,Le,DO,Je,KO/9f,PN,Eg,XN,ag,[N,Bj,lN/dj,OM,^j,_M/^j,_M,Bj,lN","n":"Vee"},{"g":"6i,J],4l,5p,Zl,e[,<n,<[,Mo,SZ,a21,JX,h31,XW,441,QW,<51,^V,Y51,HV,;61,7V,Z61,jU,^61,aU,[61,ZU,I61,OU,_51,>U,D51,2U,151,jT,151,bT","n":"Nurme"},{"g":":21,Vp,K21,Rp,?31,@p,[31,;p,J41,j[,;51,W[,c51,8[,:61,aZ,l71,>Y,D81,nX","n":"Siguri"},{"n":"Kadaka","g":"jM2,QV,NM2,NV,:M2,LV,4L2,BV,[K2,>V,LK2,:V,=K2,:V,hJ2,8V,[J2,6V,MJ2,3V,9J2,nU,BI2,fU,bH2,^U,pH2,YU"},{"g":"Bj,lN,^j,lN,Cl,5O,@l,EO,jm,PO/Fe,gX,0f,XX,>f,SX,Ah,TV,Nh,EV,Ei,YU,pi,DU,Fj,_T,Tj,ZT/8m,kR,Hm,`R/5o,7O,>o,UN,Ao,GN,Ho,0N/Hm,`R,Pm,ZR,im,DR,9n,nQ,Hn,PQ,Vn,aP/Tj,ZT,fj,PT,1m,0S,4m,nR,8m,kR/2c,KY,7d,2Y,hd,iX,Fe,gX/Vn,aP,an,<P,5o,7O","n":"P\u00e4rna pst"},{"n":"Jaun\u0101 iela","g":"J;,FE,f<,TC"},{"g":"2E1,H`,ID1,Y`,lC1,d`,>C1,5a,]B1,Aa,aA1,Wa,RA1,pa,AA1,ba,Q@1,4b,n?1,Bb,F?1,Ob","n":"Pihlaka"},{"g":"GJ2,BR,jJ2,SR,WK2,jR,[K2,mR,hK2,5S,]L2,SS,gL2,XS/WK2,jR,KN2,MQ,3O2,8Q,MO2,mP,ZO2,lP/ZO2,lP,lO2,8Q,eP2,XQ","n":"Vaarika"},{"g":"@],3W,e],GW,:^,SW,>^,UW,H^,XW,`^,^W,A`,DX,O`,LX,V`,TX,V`,`X,L`,gX,=`,1Y,W_,;Y,9_,FY,f^,OY,W^,hY","n":"Maz\u0101 Ceri\u0146u iela"},{"g":"PA,76,EA,06,o@,l5,a@,m5,f>,M6,P;,B7,N:,T7","n":"Purva iela"},{"g":"EW1,RR,8X1,EQ","n":"Saare"},{"g":";O1,hO,FP1,eM,cQ1,AK","n":"Jakobi"},{"n":"Lembitu","g":"Yd1,]F,]b1,EF,8_1,^E,C[1,3E,bV1,>D"},{"g":"Nd,oG,Dd,iG,Ad,ZG,@d,LG,Bd,AG,^d,lF,:e,YF,_f,mE,?g,eE,Cg,^E,Sh,7E,Li,pD","n":"P\u00f5llu"},{"n":"Perve","g":"<51,^V,I71,FW,091,lW,G:1,^X,0>1,cZ,2>1,oZ,f=1,9[,n<1,S[,e<1,W[/291,IY,G:1,^X/DH1,??1,:H1,^>1,4I1,A>1,:I1,1>1,jH1,]=1,pH1,5=1,SH1,p<1,pH1,i;1"},{"g":"H_1,D=,B_1,:=,T^1,W<,h]1,7<","n":"Kagu"},{"g":"PG1,<B,aF1,hB,4F1,PC,EC1,iE,;C1,7F","n":"Narva"},{"n":"Sinepi","g":"<G2,BS,7G2,GS,5G2,LS,8G2,RS,BG2,YS,5H2,mS,AH2,2T,TI2,OT,MJ2,eT"},{"n":"M\u00e4nnipuu","g":"SK2,Qp,_K2,Ap,hK2,b[,0L2,G[,?L2,bZ,RL2,2Z,TL2,lY,aL2,bY,hL2,GY,gL2,?Y,4M2,UX,DM2,0X,DM2,hW,kM2,XV,jM2,QV"},{"g":"4e1,jB,`h1,fD","n":"Heina"},{"g":"Zc,>I,fc,EI,cd,7J,hd,FJ,gd,TJ","n":"Haru"},{"n":"Pedeli","g":"4=1,1U,I>1,_S,m@1,GQ,hB1,nO,;C1,ZO,<C1,KO,kB1,pN,NB1,=N"},{"n":"Petseri","g":"bW1,oN,][1,aO,e]1,<P,=^1,BP,Q^1,KP,Z`1,:R,Ca1,[R,Ja1,aR,Ta1,kR,ob1,4T,cc1,dT,Xf1,:W,df1,OW,lf1,KX/<M1,JM,FP1,eM,]R1,8N,KT1,FN,bW1,oN"},{"g":"Li,EZ,[j,7[,4l,5p,Dm,mp,2n,M],;o,>^,?o,A^,F01,A_/dm,^^,<m,E^,bl,3^,Xl,b],Wl,Q],Zl,C],kl,9],Dm,mp","n":"Kesva"},{"g":"^F2,YZ,SH2,6Z","n":"M\u00e4dar\u00f5ika"},{"n":"K\u00f6ie","g":"?41,oF,941,6G,E31,aG,d21,CH/d21,CH,H11,VI,^01,<J,no,hJ"},{"n":"Pargi","g":"R=1,LJ,V=1,MJ,T?1,8K,X?1,9K,_?1,:K,9@1,?K,j@1,FK,WA1,JK,3B1,JK,QB1,IK,RC1,CK,>D1,AK,ND1,BK,BI1,]K,FI1,]K,[J1,gK,AK1,mK,JL1,9L,NL1,9L,<M1,AL,_M1,GL"},{"n":"\u00d5unapuu","g":"5E2,eW,KF2,fW,PG2,gW"},{"g":"3^1,2B,j]1,kA,2p1,j@,^Y1,[?,LY1,Q?,7X1,h>,DW1,O>,oV1,F>,fV1,?>,jV1,5>,6W1,h=,PW1,U=","n":"Tuubi"},{"n":"Kalevi","g":"bQ1,_?,kP1,O?,<P1,@?,2P1,>?,jO1,>?,bO1,@?,]O1,D?,DO1,Z?,pN1,>@,pM1,8A,_L1,1B,cK1,9B,7K1,?B,eJ1,?B,NJ1,<B,?J1,8B/_L1,1B,kL1,1B,9M1,2B,TM1,6B,@N1,@B,IN1,CB,0O1,MB"},{"n":"P\u00e4\u00e4susilma","g":">F2,MY,4H2,MY"},{"n":"S\u00f5le","g":"a>1,C=1,e?1,V=1,NF1,_?1,8G1,m?1,TG1,j?1,5H1,p?1,@H1,R?1,DH1,??1/IC1,F:1,EB1,E;1,4A1,N<1,e?1,V=1"},{"n":"Valli","g":"QQ1,kC,NQ1,9D,kP1,pD,KP1,>E,FP1,LE/pO1,NE,FP1,LE,4R1,HE,SR1,HE,nR1,PE,cT1,5F,6V1,IF,DV1,NF,YV1,TF,1Y1,QG,MY1,ZG,jY1,_G,]]1,>H,Ga1,^H,7d1,5I,Me1,?I,<h1,RI,hi1,^I,Ej1,fI"},{"n":"Toogi p\u00f5ik","g":"H[2,0,T[2,:,Z[2,>,g[2,J,^p2,91,R]2,f1,3^2,B2"},{"g":"Li,EZ,Oh,^Y,@h,ZY,jg,]Y,=g,2Z,Fe,gX","n":"Odra"},{"n":"M\u00e4nni","g":"bJ2,J^,2J2,l_,4J2,7`,WI2,Ja,nH2,Vb"},{"g":"2K2,mO,1K2,6P,kJ2,HP,fJ2,SP,[J2,XP,JJ2,WP,9J2,UP,OI2,UP,GI2,SP,@I2,OP,=I2,LP,;I2,AP,=I2,6P,CI2,nO,FI2,eO","n":"Iirise"},{"n":"Pu\u0161kina iela","g":"bE,nB,GH,YD,9J,^E,TJ,8F,_J,IF,hJ,iF"},{"n":"Viadukti","g":"?Y1,oL,lY1,0M,FZ1,2M,SZ1,5M,WZ1,8M,[Z1,;M,4[1,pM,U[1,8N,4p1,HN,Vp1,VN,np1,pN,X]1,cN,C^1,gN,@_1,gN,__1,cN,O`1,ZN,>a1,JN,Na1,CN,5b1,3N,Jb1,kM,`b1,dM,7c1,^M,Tc1,XM,Ed1,QM,2e1,LM,ce1,GM,Bf1,BM,df1,:M,Ag1,0M,_g1,cL,6h1,VL,Mh1,DL,[h1,2L,eh1,_K,0i1,<K,7i1,kJ,Bi1,ZJ,Si1,JJ,5j1,0J,Ej1,fI,dj1,WI,mj1,OI"},{"g":"F2,HJ,g3,WJ","n":"\u0136ir\u0161u iela"},{"g":"pp,nB,f`,`D/f`,`D,:e,YF","n":"M\u00e4e"},{"n":"Eha","g":"_D2,kb,VE2,la"},{"n":"Valdem\u0101ra iela","g":"jA,FB,_@,eA,7@,MA/7@,MA,f?,DA,O>,G@,B=,A?,_;,i="},{"n":"Andrese","g":"cW1,3C,eW1,8C,cW1,?C,bV1,>D,XU1,BE,cT1,5F"},{"g":"lF2,m[,1I2,a[","n":"Kreegipuu"},{"g":"fF2,C[,2H2,5[,gH2,kZ","n":"Kibuvitsa"},{"n":"Turu","g":"3;1,YL,p;1,_K,`;1,WK,b;1,JK,i;1,TJ,k;1,JJ"},{"g":"0I2,jR,2J2,JR,BJ2,AR,GJ2,BR,HJ2,<R,ZJ2,0R","n":"Umb"},{"n":"Domes bulv\u0101ris","g":"lA,RM,?A,hL,8A,WL,2A,HL,:A,oK,`B,iI,oC,@H,hD,5G,ZE,5F,lE,_E"},{"n":"Soo","g":"VU1,GL,PX1,oL,?Y1,oL"},{"n":"Veski","g":"0M1,b?,OL1,=@,1L1,T@,VK1,j@,?J1,8B,4H1,nC,WF1,FE"},{"g":"?G2,5Q,KG2,kP,XG2,OP,kG2,eO,mG2,^O","n":"Astra"},{"g":"Vk,NY,<n,<[,Ho,l[,:11,Op,R11,Rp,:21,Vp","n":"L\u00fchike"},{"n":"Valga - Londi","g":"6;3,l?,Z53,C@,R23,Q@,503,p@,bh2,;A,^c2,QA,T_2,dA,5_2,gA,WW2,GB,<W2,JB,GQ2,bB,KL2,7C,DF2,RC,>C2,aC,0B2,jC,E@2,AD,@?2,UD,0?2,^D"},{"g":"fP,FB,9Q,<B/9Q,<B,CQ,8B,lQ,hA,bR,TA,nR,PA,XS,@A,1T,9A,FU,Z@,IV,C@","n":"Gaujas iela"},{"g":"PW1,U=,XW1,S=,aW1,S=,1X1,W=,EX1,^=,]X1,i=,OY1,B>,WZ1,f>","n":"Talve"},{"n":"Hiie","g":"7n1,PA,?n1,FA,3o1,f@/7n1,PA,3n1,LB,4n1,JC,2n1,MC,0n1,OC,jm1,SC,ak1,]D/>o1,k@,[02,8@"},{"n":"Mooni","g":"a83,;X,_73,1X,b63,jW,[43,XW,n23,HW,B23,BW,p13,?W"},{"n":"Kaevu","g":"cJ2,cX,XJ2,bX,SJ2,^X,PJ2,XX,LJ2,MX,JJ2,DX,FJ2,=X,AJ2,1X,oI2,EW"},{"n":"P\u00e4rna","g":"6l2,ob,mj2,ka,9j2,6a,6i2,4`"},{"n":"Herne","g":"4H1,nC,4F1,PC,dC1,oB,gB1,pB,WB1,YB"},{"g":"MA,N8,Z=,]9","n":"Lauku iela"},{"g":"Q91,2`,b:1,R_,[=1,3^,Q?1,n^","n":"Kuuse"},{"n":"Energia","g":"mB1,=c,5C1,Jc,:C1,Rc,JA1,Id,L@1,gd,c?1,:e,>?1,Ke,S>1,_e,M>1,ae,U=1,9f,_<1,Ve,M<1,He,G<1,?e,B<1,8e,I<1,3e,Q<1,2e,f<1,ld,8=1,jd,G=1,md,Y=1,6e,d=1,@e,6>1,Oe,M>1,ae"},{"g":"`:2,aZ,B<2,_[,?>2,R],2@2,A_,R@2,2`,`A2,6a,SB2,Za,GC2,Jb,_D2,kb","n":"Vana-Tambre tee"},{"n":"M\u00f6\u00f6bli","g":"AU1,9Y,US1,YX,SP1,`W"},{"n":"Pirnipuu","g":"QG2,5W,_F2,5W,9E2,6W,cD2,5W,YD2,2W"},{"g":"7I2,Me,TI2,Hd,UI2,jc/GJ2,Lb,EJ2,@c,UI2,jc","n":"H\u00e4mariku"},{"n":"Lille","g":"3o1,f@,>o1,k@,`02,`A,W12,6B,[42,oB,a72,5D,R:2,5E,5;2,BE,H;2,PE/EB1,E;1,YF1,p<1/3o1,f@,;m1,f?,Lk1,o>,=k1,g>"},{"g":"DA1,fT,8D1,CR,DD1,1R","n":"J\u00f5e"},{"n":"Videviku","g":"cH2,Wb,_H2,`b,kH2,@c,>F2,_c,fE2,Ed"},{"n":"V\u00e4ike-Lepa","g":"5=1,Ta,[<1,aa,L;1,:a/Q?1,n^,_?1,0_,e@1,S_,p?1,8`,U>1,``,K>1,c`,F>1,c`,?>1,a`,8=1,=`"},{"g":"=S,hE,BT,YD,NT,LD/NT,LD,RT,GD","n":"S\u0113ru iela"},{"g":"A:1,ba,L;1,:a,V<1,O`,8=1,=`,Q?1,n^,9A1,6^","n":"Lepa"},{"n":"Austras iela","g":"PU,_T,;U,YT,1T,=T,MR,VS,5R,OS,hQ,KS"},{"g":"J4,VE,c4,gE,:5,;F,a5,NF,>6,SF,X6,VF,F9,RF,@<,OF","n":"M\u0101lu iela"},{"n":"V\u00e4ike-Laatsi","g":"Z>2,pD,0?2,^D/ZG2,gJ,ZG2,IJ,LG2,nI/ZG2,gJ,_G2,9K,]G2,[K,ZG2,hK,[G2,6L,pG2,EL,gG2,gL,jG2,7M,[G2,?M,EG2,HM,4G2,QM/0?2,^D,I?2,iD,]?2,7E,7A2,4G,pC2,BJ,jC2,JJ,CD2,SJ,cD2,YJ,ZG2,gJ"},{"g":"dj,_G,^j,[G,_j,VG,Rk,^F,Xk,ZF/Ak,dG,Dj,]H","n":"Vaikne"},{"n":"Pipra","g":"dG2,3R,_G2,:R,pG2,DR,[G2,RR,XG2,^R,VG2,fR,QG2,oR,<G2,BS"},{"n":"Semin\u0101ra iela","g":"[S,=F,1T,CF,?T,FF,=V,pF,jV,dF,9W,fF,QW,iF,9X,1G,UY,CG,dZ,[G,fp,AH,>^,]H,T_,9I,2`,?I,O`,EI,l`,II,ia,OI,na,PI/Xb,WI,^b,XI/Eb,TI,Nb,UI,Xb,WI/na,PI,Eb,TI"},{"g":"Rg1,[A,1h1,UA,Mh1,MA,Vh1,LA,fh1,IA,Qi1,KA,Hj1,RA/ok1,`B,Jk1,LB,Ak1,GB,ij1,:B,bj1,1B,Wj1,_A,Qj1,WA,Hj1,RA","n":"Peebu"},{"n":"\u00dclase","g":";F2,`R,0F2,nR,]E2,;S,PE2,9S,AE2,5S,GD2,]R/GD2,]R,oB2,<R,BA2,SQ,1A2,JQ,;@2,9Q,Y?2,lP,7?2,^P,c>2,TP"},{"n":"Valmieras iela","g":"bF,PA,cG,AA,=H,9A,HI,A@,ZI,4@"},{"g":"J],[R,h[,>S,H[,TS,^p,OT,W],@U,_^,NV","n":"Ceri\u0146u iela"},{"n":"Avotkalna iela","g":"lJ,6a,iK,I`,=M,L_,cM,;_,_R,i],6S,d],]S,]],DT,U],lT,M],QU,F],WU,A],mU,0]/LA,;@1,KB,P>1,6C,j=1,SD,0=1,^G,:;1,RH,^:1,iH,F:1,aI,S71,iJ,W41,4K,c31,@K,921,>K,T11,4K,311,aJ,L01,VJ,401,BJ,[o,II,mn,PG,Pm,;G,;m,4G,ll,cF,Zj,aF,Qj,[F,`i,1F,5e,oE,jd,:G,ic,bJ,>a"},{"n":"Vahe","g":"7p1,G<,4p1,M<,6p1,U<,=p1,p<,ap1,3=,7]1,D=,C]1,Q="},{"g":"nG2,_U,lG2,9V,hG2,PV,QG2,5W,KG2,=W,IG2,FW,JG2,PW,OG2,aW,PG2,gW,`G2,WX,eG2,gX,nG2,EY,4H2,MY,?H2,]Y,SH2,6Z,XH2,;Z,aH2,MZ,bH2,OZ,gH2,kZ,iH2,5[,1I2,a[,1I2,b[,9I2,Cp,CI2,Lp,GI2,Mp/SK2,Qp,PK2,Zp,DK2,fp,=K2,3],=K2,B],AK2,K],>K2,X],5K2,_],lJ2,i],hJ2,4^,bJ2,J^/GI2,Mp,RI2,Op,aI2,Np,SJ2,Gp,8K2,Fp,JK2,Hp,SK2,Qp","n":"Kirsipuu"},{"g":"^G1,`>,?H1,n>,mF1,8@,dC1,oB,Z?1,]F","n":"Oru"},{"g":"H;2,PE,2;2,VE,b92,iE,^52,jF,o32,FG,F12,1H,=o1,SH,1m1,5I,Nk1,MI,mj1,OI/H;2,PE,`<2,;E,Z>2,pD","n":"Saviaugu"},{"n":"Latgales iela","g":"A^,]K,F^,XK,R^,JK,j^,iJ,=_,PJ,T_,iI,2`,?I/V],fL,Z],_L,`],UL,e],ML,i],FL,A^,]K/B],3M,I],0M,O],kL,V],fL"},{"g":"fp,AH,fp,lG,Pp,WG,K[,gF,8[,[F,dZ,UF,?Z,JF,:X,0F,QW,iF","n":"K\u016bru iela"},{"n":"Br\u012bvzemnieka iela","g":"f=,MS,Q=,XS,l<,iS,3<,VT,J;,_T,A:,cT,2:,dT,X9,bT,l8,ZT,]8,UT,88,JT,08,HT,l6,@T,D5,MT,;3,YT,h2,[T,`2,`T,V2,kT,O2,1U,C2,:U,42,EU,h,]V,;,LW,0,XW"},{"n":"Haava","g":"hQ1,SR,;R1,8R,KR1,dQ,JR1,`Q,GR1,pQ,>R1,ZQ,dQ1,TQ,@Q1,NQ"},{"g":":C1,Rc,4D1,[c,bD1,dc,dE1,8d,2F1,Bd,6F1,Md,2F1,Zd,TE1,9e,?E1,Oe,dD1,ee,PD1,3f,;D1,Af,ZC1,Rf,hB1,jf,3B1,>g,@A1,Sg,4@1,9h","n":"R\u00fckkeli"},{"g":"hE2,]X,0F2,TX,8F2,SX,SG2,XX,`G2,WX","n":"Mee"},{"g":"TL2,lY,GL2,mY,TJ2,<Z,JJ2,=Z,AI2,FZ,aH2,MZ","n":"Viinamarja"},{"n":"Toogi","g":"oT2,82,=U2,B2,CU2,G2,pU2,[2,JV2,=3,YV2,G3,`V2,L3,lV2,N3,8W2,N3,GW2,J3,:X2,83,jX2,h2,JZ2,I2,=[2,82,Gp2,]1"},{"g":"?b1,d=,=e1,O=,ae1,I=,?f1,B=","n":"S\u00fcgise"},{"g":"953,F_,D63,V^,N83,D],_83,op,c83,Wp,V83,Mp,i73,Gp,n63,Bp","n":"M\u00f5mmi"},{"g":"Q`1,EC,F`1,SC,8_1,^E,]]1,>H,lp1,_I","n":"M\u00e4rdi"},{"g":"DV1,NF,3V1,cF,fU1,@G,QU1,0H","n":"Tuule"},{"n":"Paju","g":"Fe,gX,8f,eX,Rf,cX,@g,^X,Ti,7X,Gk,OW,ml,kV,Hm,`V,^m,TV,An,AV,an,kU"},{"n":"Pagari","g":"Xh1,9>,3h1,D>,jc1,R?"},{"n":"Apvien\u012bbas iela","g":"5,RL,D,lN,93,oN"},{"g":"4A1,N<1,:H1,^>1","n":"\u00d5ie"},{"n":"Kalna iela","g":"WF,jE,CG,9E,GH,YD,SK,]C"},{"n":"Nelgi","g":";B2,iS,TB2,^S,MC2,BS,GD2,]R,BE2,`Q,BE2,VQ,cD2,IQ,XC2,mP,hA2,DP,i@2,oO/5o2,]p,[o2,Ip,B03,@p,`03,Ap,i23,fp,L43,>],n43,=]"},{"n":"Antsla","g":"X`1,3J,N`1,7J,o^1,nI,lp1,_I,p[1,TI"},{"n":"Alfred Neulandi","g":"f01,eP,o01,^P,711,HP,@11,0P,S11,GO,921,=N/e01,9Q,]01,NQ,X01,[Q,L01,0R,A01,ER/e01,9Q,f01,lP,f01,eP"},{"g":"WI2,Ja,;G2,Ea","n":"P\u00f5ik"},{"g":">D2,BP,nC2,RP,dC2,]P,XC2,mP","n":"V\u00e4ike-Nelgi"},{"n":"Edela","g":"2n1,MC,Fn1,VC,Vn1,^C"},{"g":"WB1,YB,KB1,XB,AB1,]B,7A1,aC,n>1,dE,S>1,?F,K>1,FF,G>1,MF,C>1,TF","n":"Aasa"},{"n":"Smil\u0161u iela","g":"lR,NO,<S,FO,cS,;O,<T,9O,6V,5O,VV,6O,BX,AO,hY,5P,^p,WQ,np,dQ,J],[R,R^,[S,o^,0T,J_,GT,l`,JU/cS,;O,=S,:O,oR,:O"},{"g":"<b1,_=,6a1,Q=,@`1,F=,b_1,D=,H_1,D=,C]1,Q=,h[1,:>,WZ1,f>,LY1,Q?,:Y1,W?,aV1,l?,CT1,A@,6T1,C@,lS1,J@,;R1,3B,?Q1,jB,?P1,gC,6P1,oC,4P1,7D","n":"V\u00f5nnu"},{"n":"Leiva","g":"Kg1,h=,0g1,1>,ke1,E>,kd1,T>,kc1,^>,Zb1,g>"},{"n":"Tehnika","g":"3V1,cF,WT1,[F,0S1,QF,PQ1,GF,bP1,BF,gO1,<F,GN1,3F,]L1,iE,bH1,TE,jG1,OE,OG1,LE,WF1,FE"},{"n":"Puu","g":"SE1,pT,ZH1,WU,iK1,RV"},{"n":"Rahu","g":"oC1,5V,SE1,pT,aG1,_R"},{"n":"M\u00e4nniku","g":"=]1,YV,[p1,GW,R[1,`X,9[1,CY,9[1,VY,I[1,nY/M^1,eT,k_1,pR"},{"n":"Kreegi","g":"[E2,iU,PF2,=U,DG2,UT,5H2,mS"},{"g":"dm,8J,G01,[G","n":"Mesipuu"},{"g":"X`1,3J,o`1,II,Ga1,^H,]b1,EF,Rc1,oD","n":"Koidu"},{"n":"Lai","g":"?91,mI,h81,fI,^61,BI,D51,lH,d21,CH,b11,3H,=11,iG,G01,[G,en,CG,fk,pF,Xk,ZF,1k,RF,Uj,LF,Ci,=F,?g,eE"},{"n":"Tulbi","g":"Y22,T>,H22,Z>,Y12,e>,Uo1,C?,Xm1,]?,;m1,f?"},{"g":"==1,RP,G>1,QO,Y>1,BO,@@1,`M","n":"Oja"},{"n":"Muzeja iela","g":"j?,B?,2A,k>,EA,`>,aA,O>,4C,N=/aA,O>,VA,K>,g@,8>,S@,m=,F@,h=,>@,f=,6@,g=,0@,i=,g>,C>,`>,J>,_>,P>,b>,]>,`>,d>,S>,l>,B>,2?,B=,A?"},{"g":"Z>2,pD,N>2,QD,=>2,GD,@:2,EB,W92,hA,:72,c@,G42,J?,Y22,T>,?12,f=,612,b=,j02,p=","n":"Laatsi"},{"g":"5L1,PO,`L1,VO,;O1,hO,<Q1,9P,CV1,2Q,8X1,EQ,MZ1,bQ,k_1,pR,T`1,dR,Ta1,kR/B61,VK,W61,]K,3;1,YL,h;1,dL,M=1,:M,@@1,`M,g@1,hM,_A1,4N,iA1,7N,NB1,=N,YB1,>N,iB1,BN,=E1,JN,iE1,PN,SF1,VN,AG1,pN,CH1,kN,XI1,:O,5L1,PO","n":"Kungla"},{"g":"Ah,TV,mh,pV,fi,0W,oj,DW,=k,IW,Gk,OW","n":"Vainu"},{"g":"kL1,TD,0M1,JD,0O1,MB,_O1,`A,EQ1,=@,bQ1,_?,>R1,H?","n":"Tiigi"},{"g":"ES1,4[,1U1,MY,AU1,9Y,PU1,eX,WV1,LW,nW1,[U,FX1,;U,8Y1,gS,MZ1,bQ,][1,aO,Gp1,cN,Vp1,VN","n":"Karja"},{"g":"LK2,:V,OK2,4V,WK2,aU,pK2,TU,_K2,IU,_K2,BU","n":"Redise"},{"g":"?93,<W,j83,9W,>73,jV,h43,VV,U23,BV,I23,@V","n":"Riisali"},{"g":"LY1,o<,aZ1,W=,h[1,:>","n":"Kolde"},{"n":"Sireli","g":"[B2,JO,OB2,DO,EB2,BO,`A2,>O,U@2,6O,c?2,2O/1N2,:P,FN2,=P,bN2,BP,MO2,NP,YO2,XP,ZO2,lP/[B2,JO,gB2,FO,=C2,CO,_C2,CO,fD2,NO,_F2,YO,mG2,^O,FI2,eO,2K2,mO,1N2,:P"},{"n":"Gaujas Miera iela","g":"UO,CC,9P,iB,PP,UB,fP,FB"},{"n":"Ploomi","g":"a@2,aV,=A2,YV,^A2,NV,QB2,5V,hB2,iU,>C2,aU,hC2,^U,;D2,_U,OD2,aU,GE2,hU,[E2,iU,1F2,jU,bF2,fU,nG2,_U,:H2,]U,pH2,YU,gH2,VU,>I2,OU,LI2,IU,pI2,AU,BJ2,kT,MJ2,eT,<K2,OT,gL2,XS,6M2,QS,FO2,FR,HP2,fQ,eP2,XQ,kQ2,6Q,PR2,cP"},{"n":"S\u0113lijas iela","g":"hY,5P,D[,XO/0],fN,>],_N,F],[N,`^,kM/D[,XO,Z[,PO,o[,GO/pp,0O,0],fN/o[,GO,pp,0O"},{"g":"AW2,E1,QW2,R1,_W2,p1","n":"Palu p\u00f5ik"},{"g":"gY,YJ,?Z,KJ,IZ,BJ,D[,PI,d[,7I,Qp,TH,fp,AH","n":"Viestura iela"},{"n":"Roheline","g":"ib1,J_,Gb1,V_,i`1,c_,J_1,__,Yp1,@_,L[1,0_,7Y1,8^,EW1,E],1W1,6]/cd1,2X,lc1,GY,ec1,OY,[b1,mZ,Pb1,>[,?b1,7p,oa1,Yp,1b1,ep,]b1,d^,ib1,J_/lc1,GY,@e1,YY,8f1,fY,Gf1,6Z"},{"n":"Allika","g":"S:1,_S,B;1,OS,a;1,CS,G<1,nR,b<1,SR,^>1,iP,iA1,7N/_A1,4N,eA1,oM,EB1,TM,8C1,jL,AC1,aL,gC1,>L,8D1,hK,CD1,WK,ND1,BK,jD1,hI,kD1,aI/lF1,mI,nF1,gI,0G1,bI,4G1,VI,5G1,FI,`F1,BI,cE1,<I,IE1,5I,:E1,6I,7E1,<I,3E1,FI,mD1,YI,kD1,aI"},{"g":"?01,K_,2n,k_,Qm,1`,8l,A`/F01,A_,D01,F_,?01,K_","n":"Loode"},{"n":"Tirgus iela","g":"mA,RF,hD,5G,[E,?G,TF,JG,CH,^G,hI,CG,hJ,iF"},{"g":"5L1,PO,9L1,IO,<M1,JM,_M1,GL,CN1,CK,RN1,fJ","n":"Maleva"},{"n":"Peetri","g":"hC1,TY,oD1,pX,=E1,LX,VF1,AW,ZH1,WU,>K1,HS,AK1,@S,JK1,0S,OK1,dR,jK1,^Q,oK1,PQ,;L1,3Q,PL1,BP,^L1,pO,`L1,VO"},{"g":"f>,M6,^@,b7,;A,:8,MA,N8,EB,Q9,jC,;;","n":"D\u0101rza iela"},{"g":"AG2,R=,2F2,`=,VE2,j=,2E2,:>,FD2,J>,dC2,S>,6C2,X>,UA2,R>,N@2,L>,M=2,^<,K;2,J;,<;2,C;,3;2,>;,j:2,8;","n":"Hoidla tee"},{"g":"ak1,]D,Vk1,bD,Jk1,bD,;k1,^D,_h1,KC,Mf1,;B/Tf1,6B,md1,S@","n":"V\u00e4lja"},{"n":"\u00d5htu","g":"P`1,UA,p`1,`A,5b1,RB,nb1,1C,mc1,PC"},{"g":"md1,S@,jc1,R?/jc1,R?,Fc1,X?,6c1,W?,jb1,Q?,ab1,>?,Zb1,g>,Bb1,m=,?b1,d=,<b1,_=,Fa1,a;,?a1,^;,h]1,7<","n":"Kevade"},{"n":"J\u00e4rve","g":"XH2,m],0H2,Y_"},{"g":"em1,D>,Cm1,0>,`l1,`=,Ql1,T=,Hl1,H=,=l1,i<,>l1,V<,Dl1,F<,Rl1,=<,^l1,6<,jl1,n;,ol1,i;/ol1,i;,ol1,d;,gl1,p;,Kl1,L;,`k1,7;/Dl1,F<,=l1,?<,5l1,<<,_k1,8<,Fk1,5<,aj1,o;,Uj1,j;,Rj1,f;/Om1,::,Vl1,X:,`k1,7;,Xj1,_;,Rj1,f;","n":"Torni"},{"n":"Pedeles iela","g":"[C,NQ,9C,5Q,hA,BP,p?,lN,3?,LN"},{"n":"V\u00f5sa","g":"4J2,7`,@K2,A`,@K2,P`,HJ2,Jb,GJ2,Lb"},{"n":"Kalda","g":"Rb,RC,f`,`D/f`,`D,l^,LF"},{"g":"ll,DI,Mm,cH,cm,JH,dm,EH,]m,BH,Ak,dG,dj,_G/dj,_G,Ui,RG","n":"Liiva"},{"g":"I8,VD,68,mD,b7,@E,B7,SE,_6,kE,>6,SF/R4,YI,g3,WJ,Z3,2K,N3,bK,93,QL,l2,]L,e2,1M,h2,`N,h2,nN,93,oN","n":"Pumpura iela"},{"g":"YM,bP,ZN,4P,KO,UO,kO,EO,EP,>O/EP,>O,SP,=O,aP,>O,bR,MO,lR,NO","n":"Strautu iela"},{"g":"YD2,2W,PD2,iV,JD2,[V,ID2,GV,>D2,fU,;D2,_U","n":"Ojaperve"},{"g":"f11,gV,>o,IX,>n,`X,nl,1Y,Vk,NY,Li,EZ,Cf,d[","n":"Savi"},{"n":"P\u00f5hja","g":"Pe,E[,Ce,L[,9e,[[,Xd,8]"},{"g":"7i,LH,ih,UH,Zh,bH,[h,jH/<e,_J,Jf,kI,Yg,:I,ag,7I,lg,8I,ng,8I,7h,;I","n":"Uus-Sepa"},{"g":"oV,YY,ZX,gY,1Y,hY,>Y,aY,DY,SY,AY,dX,@Y,6X,>Y,bW,0Y,YW,PW,6W,[U,KV,;T,hU,iR,JU,^R,HU,9R,BU,VQ,=U,IQ,=U","n":"Fr\u012b\u010da Rozi\u0146a iela"},{"g":"=E1,LX,IC1,TW/oD1,pX,RH1,dY","n":"T\u00f6\u00f6stuse"},{"g":"1A2,JQ,BA2,oP,`A2,QP,hA2,DP,8B2,nO,LB2,RO,[B2,JO","n":"Sinilille"},{"n":"Ringtee","g":"SH1,p<1,lH1,c<1,WJ1,]<1,LK1,X<1,]K1,p<1,eK1,m<1,jK1,c=1,dK1,l=1,QJ1,I>1,:J1,J>1,pI1,9>1,lH1,c<1"},{"n":"Raudtee","g":"B<1,fF,Y;1,`F,G91,RF,c61,BF,h41,3F,=31,aE,j11,QE,^01,DE,I01,?E/I01,?E,h01,UD,o01,KD,o01,FD,m01,AD,O11,ZC,J11,TC,?11,RC,211,RC,i01,XC,a01,aC,[o,5E"},{"n":"Toominga","g":"<@2,?N,9@2,<N,K?2,8N,5?2,6N,X>2,6N,e<2,jM,R<2,dM,<<2,ZM,g;2,VM,D;2,VM,J:2,RM"},{"g":"lA,RM,UB,nM,hD,WO,SE,7P","n":"\u0112r\u0123emes iela"},{"g":"o61,2S,h71,;R,Q81,UQ,H:1,kO,c:1,RO,Y;1,bN,a;1,[N,F=1,@M,M=1,:M,T=1,4M,_?1,:K,5@1,gJ,R@1,NJ,7A1,0J,:A1,mI,FA1,cI,JA1,_I,VA1,UI,]A1,OI","n":"Ernst Enno"},{"n":"Hommiku","g":"fE2,Ed,UI2,jc"},{"g":">c1,c;,Gc1,g;,mc1,9<,Ud1,M<,Oe1,e<,he1,2=,?f1,B=,Kg1,h=,`g1,5>,3h1,D>/h]1,7<,Qp1,?<,Bp1,B<,7p1,G<","n":"Suve"},{"g":":21,Vp,p51,o^,e61,]_,[71,3`,C81,P`,B81,_`","n":"Ravila"},{"n":"Kase","g":"aO1,;R,hQ1,SR,cT1,4S,8Y1,gS,M^1,eT,j^1,jT/On2,;],4n2,lp,4m2,ap,Pl2,Yp,Vl2,Ep,Tm2,5[,4n2,KZ,Cn2,=Z,fn2,AZ,[o2,JZ,603,PZ"},{"g":"mj1,OI,0k1,@I,lj1,3I,Zj1,eH,Ti1,?H,Vh1,pG,^g1,=G,Qf1,SF,ke1,?F,2e1,`E,Rc1,oD,Gb1,ED,Q`1,EC,=_1,XB,M^1,=B,>^1,0B","n":"L\u00f5una"},{"g":"pi,DU,=m,HV,^m,TV","n":"Telliskivi"},{"n":"Sipelga","g":"Kl2,J`,Kk2,[`,9j2,6a"},{"n":"Kirde","g":"2F1,Bd,IF1,Dd,aF1,Hd,KG1,Wd,iG1,`d,:H1,jd,DH1,8e,TH1,Ce,iH1,Pe,<I1,_e,KI1,1f,SI1,Gf"},{"g":"I6,7D,I8,VD,J;,FE,0=,pE","n":"Za\u013c\u0101 iela"},{"g":"hA,BP,^A,HP,2@,FQ,<>,4S,i=,DS,f=,MS,1@,5T,E@,AT","n":"C\u0113su iela"},{"n":"Stendera iela","g":"8Q,ID,kP,MD,QO,kD,;N,GE,bM,RE,KL,mE,2L,1F,YK,6F,2K,BF,_J,IF"},{"g":"L;1,:a,Q91,2`,l61,V^,461,o],i31,?p,[31,;p,F31,:p,231,8p,E21,f[","n":"R\u00e4ni"},{"g":"^c1,XC,;d1,fC,3e1,DD,mf1,DE,Ug1,XE","n":"Tehase"},{"g":"_D2,kb,OF2,mb,cH2,Wb,nH2,Vb,GJ2,Lb","n":"Valguse"},{"g":"bo,jI,^01,<J","n":"V\u00e4ike-K\u00f6ie"},{"n":"Metsa\u00e4\u00e4re","g":"n43,=],^53,gp,O63,Pp,n63,Bp,V73,O[,k73,VZ,083,GZ,683,1Z,>83,JY,U83,XX,a83,;X,g83,1X,=93,NW,?93,<W"},{"n":"Kelli tee","g":"SI1,Gf,RI1,Yf,TI1,kf,YI1,4g,lI1,Mg,EJ1,mg,QJ1,>h,0K1,Hh,`K1,Jh,bL1,Ih/4P1,Uf,fO1,]f,DO1,2g,OM1,lg,jL1,@h,bL1,Ih,gL1,Sh,;M1,bh,0N1,Ji,MN1,6j,^N1,hj,^N1,Ek,NN1,Sk,2N1,ik,HL1,al,jG1,0o,8G1,Io,YF1,Uo,9F1,Zo,`?1,fo,X=1,io,;71,201,B21,801,bo,A01,Yo,A01"},{"n":"Saaremaja metsavahi tee","g":"fc2,Uo,2e2,;n,Be2,em,Se2,Mm,8h2,9k,Xk2,kg,ek2,bg"},{"n":"Maasika","g":"YI2,8Y,0J2,ZY,JJ2,=Z"},{"n":"L\u012bvu iela","g":">,eH,01,oH,Y1,7I,p1,8I,X2,CI,K3,MI,64,UI,R4,YI,n7,BJ"},{"n":"Poruka iela","g":"6L,>A,iK,AA,pK,EA,fJ,NA,`J,OA,bI,VA,7I,]A,SH,fA,VF,PB,bE,nB,9E,JC,SD,fC,gC,ND,=C,5E,mA,RF,T@,6H,0@,^H,5@,mH,<@,7I"},{"g":"SH,fA,SK,]C,KL,AD,MM,lD,VM,2E,;N,GE,_N,eE,GO,`F,4P,DG","n":"Mer\u0137e\u013ca iela"}],"y":57.75844,"x":25.9946,"precision":5}